basenji2_pytorch/__init__.py
basenji2_pytorch/blocks.py
basenji2_pytorch/model.py
basenji2_pytorch-0.1.2.dist-info/METADATA
basenji2_pytorch-0.1.2.dist-info/WHEEL
basenji2_pytorch-0.1.2.dist-info/licenses/LICENSE
basenji2_pytorch-0.1.2.dist-info/RECORD
