Metadata-Version: 2.4
Name: basenji2-pytorch
Version: 0.1.2
Summary: PyTorch implementation of Basenji2
License-File: LICENSE
Requires-Python: >=3.9
Requires-Dist: einops>=0.7.0
Requires-Dist: natsort>=8.4.0
Requires-Dist: numpy>=1.22
Requires-Dist: pooch>=1.8.2
Requires-Dist: pytorch-lightning>=2
Requires-Dist: torch>=2
Requires-Dist: torchinfo>=1.8.0
Requires-Dist: torchmetrics>=1.6.2
